get_eyedata/__init__.py
get_eyedata/frame_utils.py
get_eyedata/ow2.py
get_eyedata/valo.py
get_eyedata/video_edit.py
get_eyedata-1.3.4.dist-info/LICENCE
get_eyedata-1.3.4.dist-info/METADATA
get_eyedata-1.3.4.dist-info/WHEEL
get_eyedata-1.3.4.dist-info/top_level.txt
get_eyedata-1.3.4.dist-info/RECORD
