Metadata-Version: 2.1
Name: get-eyedata
Version: 1.3.4
Summary: gat gaze data form record.
Home-page: https://github.com/ikrfun/get_eyedata
Download-URL: https://github.com/ikrfun/get_eyedata
Author: ikrfun
Author-email: t.nobuto130625@gmail.com
Maintainer: ikrfun
Maintainer-email: t.nobuto130625@gmail.com
License: MIT
Keywords: gaze game
Classifier: License :: OSI Approved :: MIT License
Classifier: Programming Language :: Python :: 3.10
License-File: LICENCE
Requires-Dist: matplotlib (>=3.7.1)
Requires-Dist: moviepy (>=1.0.3)
Requires-Dist: numpy (>=1.24.3)
Requires-Dist: opencv-contrib-python (>=4.6.0.66)
Requires-Dist: opencv-python (>=4.7.0.72)
Requires-Dist: opencv-python-headless (>=4.7.0.72)
Requires-Dist: pandas (>=2.0.2)
Requires-Dist: setuptools (>=67.8.0)
Requires-Dist: tqdm (>=4.65.0)
Requires-Dist: utils (>=1.0.1)
